{
  "last_node_id": 212,
  "last_link_id": 252,
  "nodes": [
    {
      "id": 134,
      "type": "easy showAnything",
      "pos": {
        "0": -1100,
        "1": 910
      },
      "size": {
        "0": 210,
        "1": 80
      },
      "flags": {},
      "order": 43,
      "mode": 0,
      "inputs": [
        {
          "name": "anything",
          "type": "*",
          "link": 102,
          "shape": 7
        }
      ],
      "outputs": [],
      "properties": {
        "Node name for S&R": "easy showAnything"
      },
      "widgets_values": [
        "false"
      ]
    },
    {
      "id": 132,
      "type": "easy showAnything",
      "pos": {
        "0": -1100,
        "1": 1140
      },
      "size": {
        "0": 210,
        "1": 80
      },
      "flags": {},
      "order": 45,
      "mode": 0,
      "inputs": [
        {
          "name": "anything",
          "type": "*",
          "link": 104,
          "shape": 7
        }
      ],
      "outputs": [],
      "properties": {
        "Node name for S&R": "easy showAnything"
      },
      "widgets_values": [
        "false"
      ]
    },
    {
      "id": 133,
      "type": "easy showAnything",
      "pos": {
        "0": -1100,
        "1": 1020
      },
      "size": {
        "0": 210,
        "1": 80
      },
      "flags": {},
      "order": 44,
      "mode": 0,
      "inputs": [
        {
          "name": "anything",
          "type": "*",
          "link": 103,
          "shape": 7
        }
      ],
      "outputs": [],
      "properties": {
        "Node name for S&R": "easy showAnything"
      },
      "widgets_values": [
        "false"
      ]
    },
    {
      "id": 117,
      "type": "easy showAnything",
      "pos": {
        "0": -1870,
        "1": 310
      },
      "size": {
        "0": 210,
        "1": 80
      },
      "flags": {},
      "order": 32,
      "mode": 0,
      "inputs": [
        {
          "name": "anything",
          "type": "*",
          "link": 114,
          "shape": 7
        }
      ],
      "outputs": [],
      "properties": {
        "Node name for S&R": "easy showAnything"
      },
      "widgets_values": [
        "0"
      ]
    },
    {
      "id": 118,
      "type": "easy showAnything",
      "pos": {
        "0": -1870,
        "1": 170
      },
      "size": {
        "0": 210,
        "1": 80
      },
      "flags": {},
      "order": 31,
      "mode": 0,
      "inputs": [
        {
          "name": "anything",
          "type": "*",
          "link": 113,
          "shape": 7
        }
      ],
      "outputs": [],
      "properties": {
        "Node name for S&R": "easy showAnything"
      },
      "widgets_values": [
        "0"
      ]
    },
    {
      "id": 116,
      "type": "easy showAnything",
      "pos": {
        "0": -1870,
        "1": 40
      },
      "size": {
        "0": 210,
        "1": 80
      },
      "flags": {},
      "order": 30,
      "mode": 0,
      "inputs": [
        {
          "name": "anything",
          "type": "*",
          "link": 112,
          "shape": 7
        }
      ],
      "outputs": [],
      "properties": {
        "Node name for S&R": "easy showAnything"
      },
      "widgets_values": [
        "0"
      ]
    },
    {
      "id": 146,
      "type": "VrchXYZOSCControlNode",
      "pos": {
        "0": -2286,
        "1": 29
      },
      "size": {
        "0": 315,
        "1": 650
      },
      "flags": {},
      "order": 16,
      "mode": 0,
      "inputs": [
        {
          "name": "server_ip",
          "type": "STRING",
          "link": 232,
          "widget": {
            "name": "server_ip"
          }
        },
        {
          "name": "port",
          "type": "INT",
          "link": 243,
          "widget": {
            "name": "port"
          }
        }
      ],
      "outputs": [
        {
          "name": "X_INT",
          "type": "INT",
          "links": [
            112
          ],
          "slot_index": 0,
          "shape": 3
        },
        {
          "name": "Y_INT",
          "type": "INT",
          "links": [
            113
          ],
          "slot_index": 1,
          "shape": 3
        },
        {
          "name": "Z_INT",
          "type": "INT",
          "links": [
            114
          ],
          "slot_index": 2,
          "shape": 3
        },
        {
          "name": "X_FLOAT",
          "type": "FLOAT",
          "links": null,
          "shape": 3
        },
        {
          "name": "Y_FLOAT",
          "type": "FLOAT",
          "links": null,
          "shape": 3
        },
        {
          "name": "Z_FLOAT",
          "type": "FLOAT",
          "links": null,
          "shape": 3
        },
        {
          "name": "X_RAW",
          "type": "FLOAT",
          "links": null,
          "shape": 3
        },
        {
          "name": "Y_RAW",
          "type": "FLOAT",
          "links": null,
          "shape": 3
        },
        {
          "name": "Z_RAW",
          "type": "FLOAT",
          "links": null,
          "shape": 3
        }
      ],
      "properties": {
        "Node name for S&R": "VrchXYZOSCControlNode"
      },
      "widgets_values": [
        "192.168.123.104",
        8000,
        "/3/xyz",
        0,
        1,
        0,
        100,
        false,
        0,
        1,
        0,
        100,
        false,
        0,
        1,
        0,
        100,
        false,
        false
      ]
    },
    {
      "id": 152,
      "type": "VrchAnyOSCControlNode",
      "pos": {
        "0": -2280,
        "1": 1593
      },
      "size": {
        "0": 315,
        "1": 190
      },
      "flags": {},
      "order": 22,
      "mode": 0,
      "inputs": [
        {
          "name": "server_ip",
          "type": "STRING",
          "link": 238,
          "widget": {
            "name": "server_ip"
          }
        },
        {
          "name": "port",
          "type": "INT",
          "link": 249,
          "widget": {
            "name": "port"
          }
        }
      ],
      "outputs": [
        {
          "name": "INT",
          "type": "INT",
          "links": [
            119
          ],
          "slot_index": 0,
          "shape": 3
        },
        {
          "name": "FLOAT",
          "type": "FLOAT",
          "links": [
            120
          ],
          "slot_index": 1,
          "shape": 3
        },
        {
          "name": "TEXT",
          "type": "STRING",
          "links": [
            121
          ],
          "slot_index": 2,
          "shape": 3
        },
        {
          "name": "BOOL",
          "type": "BOOLEAN",
          "links": [
            122
          ],
          "slot_index": 3,
          "shape": 3
        }
      ],
      "properties": {
        "Node name for S&R": "VrchAnyOSCControlNode"
      },
      "widgets_values": [
        "192.168.123.104",
        8000,
        "/data/gameController/shoulder/left",
        false
      ]
    },
    {
      "id": 149,
      "type": "easy showAnything",
      "pos": {
        "0": -1866,
        "1": 1594
      },
      "size": {
        "0": 210,
        "1": 76
      },
      "flags": {},
      "order": 47,
      "mode": 0,
      "inputs": [
        {
          "name": "anything",
          "type": "*",
          "link": 119,
          "shape": 7
        }
      ],
      "outputs": [],
      "properties": {
        "Node name for S&R": "easy showAnything"
      },
      "widgets_values": [
        "0"
      ]
    },
    {
      "id": 151,
      "type": "easy showAnything",
      "pos": {
        "0": -1873,
        "1": 1728
      },
      "size": {
        "0": 210,
        "1": 76.00006103515625
      },
      "flags": {},
      "order": 48,
      "mode": 0,
      "inputs": [
        {
          "name": "anything",
          "type": "*",
          "link": 120,
          "shape": 7
        }
      ],
      "outputs": [],
      "properties": {
        "Node name for S&R": "easy showAnything"
      },
      "widgets_values": [
        "0.0"
      ]
    },
    {
      "id": 150,
      "type": "easy showAnything",
      "pos": {
        "0": -1868,
        "1": 1870
      },
      "size": {
        "0": 210,
        "1": 76
      },
      "flags": {},
      "order": 49,
      "mode": 0,
      "inputs": [
        {
          "name": "anything",
          "type": "*",
          "link": 121,
          "shape": 7
        }
      ],
      "outputs": [],
      "properties": {
        "Node name for S&R": "easy showAnything"
      },
      "widgets_values": [
        ""
      ]
    },
    {
      "id": 148,
      "type": "easy showAnything",
      "pos": {
        "0": -1867,
        "1": 2011
      },
      "size": {
        "0": 210,
        "1": 76
      },
      "flags": {},
      "order": 50,
      "mode": 0,
      "inputs": [
        {
          "name": "anything",
          "type": "*",
          "link": 122,
          "shape": 7
        }
      ],
      "outputs": [],
      "properties": {
        "Node name for S&R": "easy showAnything"
      },
      "widgets_values": [
        "false"
      ]
    },
    {
      "id": 100,
      "type": "easy showAnything",
      "pos": {
        "0": -1894,
        "1": -447
      },
      "size": {
        "0": 210,
        "1": 80
      },
      "flags": {},
      "order": 27,
      "mode": 0,
      "inputs": [
        {
          "name": "anything",
          "type": "*",
          "link": 111,
          "shape": 7
        }
      ],
      "outputs": [],
      "properties": {
        "Node name for S&R": "easy showAnything"
      },
      "widgets_values": [
        "0"
      ]
    },
    {
      "id": 99,
      "type": "easy showAnything",
      "pos": {
        "0": -1890,
        "1": -596
      },
      "size": {
        "0": 210,
        "1": 80
      },
      "flags": {},
      "order": 26,
      "mode": 0,
      "inputs": [
        {
          "name": "anything",
          "type": "*",
          "link": 110,
          "shape": 7
        }
      ],
      "outputs": [],
      "properties": {
        "Node name for S&R": "easy showAnything"
      },
      "widgets_values": [
        "0"
      ]
    },
    {
      "id": 153,
      "type": "easy showAnything",
      "pos": {
        "0": -1895,
        "1": -311
      },
      "size": {
        "0": 210,
        "1": 80
      },
      "flags": {},
      "order": 28,
      "mode": 0,
      "inputs": [
        {
          "name": "anything",
          "type": "*",
          "link": 123,
          "shape": 7
        }
      ],
      "outputs": [],
      "properties": {
        "Node name for S&R": "easy showAnything"
      },
      "widgets_values": [
        "0.0"
      ]
    },
    {
      "id": 154,
      "type": "easy showAnything",
      "pos": {
        "0": -1889,
        "1": -176
      },
      "size": {
        "0": 210,
        "1": 80
      },
      "flags": {},
      "order": 29,
      "mode": 0,
      "inputs": [
        {
          "name": "anything",
          "type": "*",
          "link": 124,
          "shape": 7
        }
      ],
      "outputs": [],
      "properties": {
        "Node name for S&R": "easy showAnything"
      },
      "widgets_values": [
        "0.0"
      ]
    },
    {
      "id": 141,
      "type": "VrchTextSwitchOSCControlNode",
      "pos": {
        "0": -1904,
        "1": 939
      },
      "size": {
        "0": 345.6325988769531,
        "1": 529.130859375
      },
      "flags": {},
      "order": 21,
      "mode": 0,
      "inputs": [
        {
          "name": "server_ip",
          "type": "STRING",
          "link": 237,
          "widget": {
            "name": "server_ip"
          }
        },
        {
          "name": "port",
          "type": "INT",
          "link": 248,
          "widget": {
            "name": "port"
          }
        }
      ],
      "outputs": [
        {
          "name": "TEXT_OUTPUT",
          "type": "STRING",
          "links": [
            106
          ],
          "slot_index": 0,
          "shape": 3
        }
      ],
      "properties": {
        "Node name for S&R": "VrchTextSwitchOSCControlNode"
      },
      "widgets_values": [
        "1",
        "2",
        "3",
        "4",
        "5",
        "6",
        "7",
        "8",
        "192.168.123.104",
        8000,
        "/3/radio1",
        false
      ]
    },
    {
      "id": 172,
      "type": "easy showAnything",
      "pos": {
        "0": -788,
        "1": 1701
      },
      "size": {
        "0": 210,
        "1": 76
      },
      "flags": {},
      "order": 52,
      "mode": 0,
      "inputs": [
        {
          "name": "anything",
          "type": "*",
          "link": 136,
          "shape": 7
        }
      ],
      "outputs": [],
      "properties": {
        "Node name for S&R": "easy showAnything"
      },
      "widgets_values": [
        "bbb"
      ]
    },
    {
      "id": 176,
      "type": "String",
      "pos": {
        "0": -1519,
        "1": 1695
      },
      "size": {
        "0": 210,
        "1": 58
      },
      "flags": {},
      "order": 0,
      "mode": 0,
      "inputs": [],
      "outputs": [
        {
          "name": "STRING",
          "type": "STRING",
          "links": [
            140
          ],
          "slot_index": 0,
          "shape": 3
        }
      ],
      "properties": {
        "Node name for S&R": "String"
      },
      "widgets_values": [
        "aaa"
      ]
    },
    {
      "id": 177,
      "type": "String",
      "pos": {
        "0": -1518,
        "1": 1797
      },
      "size": {
        "0": 210,
        "1": 58
      },
      "flags": {},
      "order": 1,
      "mode": 0,
      "inputs": [],
      "outputs": [
        {
          "name": "STRING",
          "type": "STRING",
          "links": [
            141
          ],
          "slot_index": 0,
          "shape": 3
        }
      ],
      "properties": {
        "Node name for S&R": "String"
      },
      "widgets_values": [
        "bbb"
      ]
    },
    {
      "id": 178,
      "type": "Int",
      "pos": {
        "0": -1513,
        "1": 1903
      },
      "size": {
        "0": 210,
        "1": 58
      },
      "flags": {},
      "order": 2,
      "mode": 0,
      "inputs": [],
      "outputs": [
        {
          "name": "INT",
          "type": "INT",
          "links": [
            142
          ],
          "slot_index": 0,
          "shape": 3
        }
      ],
      "properties": {
        "Node name for S&R": "Int"
      },
      "widgets_values": [
        111
      ]
    },
    {
      "id": 179,
      "type": "Int",
      "pos": {
        "0": -1517,
        "1": 2000
      },
      "size": {
        "0": 210,
        "1": 58
      },
      "flags": {},
      "order": 3,
      "mode": 0,
      "inputs": [],
      "outputs": [
        {
          "name": "INT",
          "type": "INT",
          "links": [
            143
          ],
          "slot_index": 0,
          "shape": 3
        }
      ],
      "properties": {
        "Node name for S&R": "Int"
      },
      "widgets_values": [
        222
      ]
    },
    {
      "id": 180,
      "type": "Float",
      "pos": {
        "0": -1514,
        "1": 2096
      },
      "size": {
        "0": 210,
        "1": 58.0545768737793
      },
      "flags": {},
      "order": 4,
      "mode": 0,
      "inputs": [],
      "outputs": [
        {
          "name": "FLOAT",
          "type": "FLOAT",
          "links": [
            144
          ],
          "slot_index": 0,
          "shape": 3
        }
      ],
      "properties": {
        "Node name for S&R": "Float"
      },
      "widgets_values": [
        1.11
      ]
    },
    {
      "id": 181,
      "type": "Float",
      "pos": {
        "0": -1514,
        "1": 2192
      },
      "size": {
        "0": 210,
        "1": 58.0545768737793
      },
      "flags": {},
      "order": 5,
      "mode": 0,
      "inputs": [],
      "outputs": [
        {
          "name": "FLOAT",
          "type": "FLOAT",
          "links": [
            145
          ],
          "slot_index": 0,
          "shape": 3
        }
      ],
      "properties": {
        "Node name for S&R": "Float"
      },
      "widgets_values": [
        2.22
      ]
    },
    {
      "id": 171,
      "type": "VrchChannelX4OSCControlNode",
      "pos": {
        "0": -1215,
        "1": 1693
      },
      "size": {
        "0": 380.4000244140625,
        "1": 342
      },
      "flags": {},
      "order": 24,
      "mode": 0,
      "inputs": [
        {
          "name": "any_channel_1_on",
          "type": "*",
          "link": 140
        },
        {
          "name": "any_channel_1_off",
          "type": "*",
          "link": 141
        },
        {
          "name": "any_channel_2_on",
          "type": "*",
          "link": 142
        },
        {
          "name": "any_channel_2_off",
          "type": "*",
          "link": 143
        },
        {
          "name": "any_channel_3_on",
          "type": "*",
          "link": 144
        },
        {
          "name": "any_channel_3_off",
          "type": "*",
          "link": 145
        },
        {
          "name": "any_channel_4_on",
          "type": "*",
          "link": 146
        },
        {
          "name": "any_channel_4_off",
          "type": "*",
          "link": 147
        },
        {
          "name": "server_ip",
          "type": "STRING",
          "link": 240,
          "widget": {
            "name": "server_ip"
          }
        },
        {
          "name": "port",
          "type": "INT",
          "link": 251,
          "widget": {
            "name": "port"
          }
        }
      ],
      "outputs": [
        {
          "name": "ANY_OUTPUT_1",
          "type": "*",
          "links": [
            136
          ],
          "slot_index": 0,
          "shape": 3
        },
        {
          "name": "ANY_OUTPUT_2",
          "type": "*",
          "links": [
            137
          ],
          "slot_index": 1,
          "shape": 3
        },
        {
          "name": "ANY_OUTPUT_3",
          "type": "*",
          "links": [
            138
          ],
          "slot_index": 2,
          "shape": 3
        },
        {
          "name": "ANY_OUTPUT_4",
          "type": "*",
          "links": [
            139
          ],
          "slot_index": 3,
          "shape": 3
        }
      ],
      "properties": {
        "Node name for S&R": "VrchChannelX4OSCControlNode"
      },
      "widgets_values": [
        "192.168.123.104",
        8000,
        "/3/toggle1",
        "/3/toggle2",
        "/3/push1",
        "/3/push2",
        false
      ]
    },
    {
      "id": 182,
      "type": "Bool",
      "pos": {
        "0": -1508,
        "1": 2314
      },
      "size": {
        "0": 210,
        "1": 58
      },
      "flags": {},
      "order": 6,
      "mode": 0,
      "inputs": [],
      "outputs": [
        {
          "name": "BOOLEAN",
          "type": "BOOLEAN",
          "links": [
            146
          ],
          "slot_index": 0,
          "shape": 3
        }
      ],
      "properties": {
        "Node name for S&R": "Bool"
      },
      "widgets_values": [
        true
      ]
    },
    {
      "id": 183,
      "type": "Bool",
      "pos": {
        "0": -1508,
        "1": 2420
      },
      "size": {
        "0": 210,
        "1": 58
      },
      "flags": {},
      "order": 7,
      "mode": 0,
      "inputs": [],
      "outputs": [
        {
          "name": "BOOLEAN",
          "type": "BOOLEAN",
          "links": [
            147
          ],
          "slot_index": 0,
          "shape": 3
        }
      ],
      "properties": {
        "Node name for S&R": "Bool"
      },
      "widgets_values": [
        false
      ]
    },
    {
      "id": 173,
      "type": "easy showAnything",
      "pos": {
        "0": -791,
        "1": 1831
      },
      "size": {
        "0": 210,
        "1": 76.00006103515625
      },
      "flags": {},
      "order": 53,
      "mode": 0,
      "inputs": [
        {
          "name": "anything",
          "type": "*",
          "link": 137,
          "shape": 7
        }
      ],
      "outputs": [],
      "properties": {
        "Node name for S&R": "easy showAnything"
      },
      "widgets_values": [
        "222"
      ]
    },
    {
      "id": 174,
      "type": "easy showAnything",
      "pos": {
        "0": -793,
        "1": 1965
      },
      "size": {
        "0": 210,
        "1": 76.00003051757812
      },
      "flags": {},
      "order": 54,
      "mode": 0,
      "inputs": [
        {
          "name": "anything",
          "type": "*",
          "link": 138,
          "shape": 7
        }
      ],
      "outputs": [],
      "properties": {
        "Node name for S&R": "easy showAnything"
      },
      "widgets_values": [
        "2.22"
      ]
    },
    {
      "id": 175,
      "type": "easy showAnything",
      "pos": {
        "0": -791,
        "1": 2109
      },
      "size": {
        "0": 210,
        "1": 76.00011444091797
      },
      "flags": {},
      "order": 55,
      "mode": 0,
      "inputs": [
        {
          "name": "anything",
          "type": "*",
          "link": 139,
          "shape": 7
        }
      ],
      "outputs": [],
      "properties": {
        "Node name for S&R": "easy showAnything"
      },
      "widgets_values": [
        "false"
      ]
    },
    {
      "id": 167,
      "type": "String",
      "pos": {
        "0": -1508,
        "1": 1549
      },
      "size": {
        "0": 226.056640625,
        "1": 58
      },
      "flags": {},
      "order": 8,
      "mode": 0,
      "inputs": [],
      "outputs": [
        {
          "name": "STRING",
          "type": "STRING",
          "links": [
            134
          ],
          "slot_index": 0,
          "shape": 3
        }
      ],
      "properties": {
        "Node name for S&R": "String"
      },
      "widgets_values": [
        "bbb"
      ]
    },
    {
      "id": 166,
      "type": "String",
      "pos": {
        "0": -1507,
        "1": 1425
      },
      "size": {
        "0": 231.2980194091797,
        "1": 58
      },
      "flags": {},
      "order": 9,
      "mode": 0,
      "inputs": [],
      "outputs": [
        {
          "name": "STRING",
          "type": "STRING",
          "links": [
            133
          ],
          "slot_index": 0,
          "shape": 3
        }
      ],
      "properties": {
        "Node name for S&R": "String"
      },
      "widgets_values": [
        "aaa"
      ]
    },
    {
      "id": 168,
      "type": "VrchChannelOSCControlNode",
      "pos": {
        "0": -1214,
        "1": 1420
      },
      "size": {
        "0": 315,
        "1": 150
      },
      "flags": {},
      "order": 23,
      "mode": 0,
      "inputs": [
        {
          "name": "any_channel_on",
          "type": "*",
          "link": 133
        },
        {
          "name": "any_channel_off",
          "type": "*",
          "link": 134
        },
        {
          "name": "server_ip",
          "type": "STRING",
          "link": 239,
          "widget": {
            "name": "server_ip"
          }
        },
        {
          "name": "port",
          "type": "INT",
          "link": 250,
          "widget": {
            "name": "port"
          }
        }
      ],
      "outputs": [
        {
          "name": "ANY_OUTPUT",
          "type": "*",
          "links": [
            135
          ],
          "slot_index": 0,
          "shape": 3
        }
      ],
      "properties": {
        "Node name for S&R": "VrchChannelOSCControlNode"
      },
      "widgets_values": [
        "192.168.123.104",
        8000,
        "/3/toggle1",
        false
      ]
    },
    {
      "id": 163,
      "type": "easy showAnything",
      "pos": {
        "0": -824,
        "1": 1418
      },
      "size": {
        "0": 210,
        "1": 76
      },
      "flags": {},
      "order": 51,
      "mode": 0,
      "inputs": [
        {
          "name": "anything",
          "type": "*",
          "link": 135,
          "shape": 7
        }
      ],
      "outputs": [],
      "properties": {
        "Node name for S&R": "easy showAnything"
      },
      "widgets_values": [
        "bbb"
      ]
    },
    {
      "id": 145,
      "type": "VrchXYOSCControlNode",
      "pos": {
        "0": -2289,
        "1": -509
      },
      "size": {
        "0": 315,
        "1": 470
      },
      "flags": {},
      "order": 15,
      "mode": 0,
      "inputs": [
        {
          "name": "server_ip",
          "type": "STRING",
          "link": 231,
          "widget": {
            "name": "server_ip"
          }
        },
        {
          "name": "port",
          "type": "INT",
          "link": 242,
          "widget": {
            "name": "port"
          }
        }
      ],
      "outputs": [
        {
          "name": "X_INT",
          "type": "INT",
          "links": [
            110
          ],
          "slot_index": 0,
          "shape": 3
        },
        {
          "name": "Y_INT",
          "type": "INT",
          "links": [
            111
          ],
          "slot_index": 1,
          "shape": 3
        },
        {
          "name": "X_FLOAT",
          "type": "FLOAT",
          "links": [
            123
          ],
          "slot_index": 2,
          "shape": 3
        },
        {
          "name": "Y_FLOAT",
          "type": "FLOAT",
          "links": [
            124
          ],
          "slot_index": 3,
          "shape": 3
        },
        {
          "name": "X_RAW",
          "type": "FLOAT",
          "links": null,
          "shape": 3
        },
        {
          "name": "Y_RAW",
          "type": "FLOAT",
          "links": null,
          "shape": 3
        }
      ],
      "properties": {
        "Node name for S&R": "VrchXYOSCControlNode"
      },
      "widgets_values": [
        "192.168.123.104",
        8000,
        "/3/xy1",
        0,
        1,
        0,
        100,
        false,
        0,
        1,
        0,
        100,
        false,
        false
      ]
    },
    {
      "id": 144,
      "type": "VrchIntOSCControlNode",
      "pos": {
        "0": -1550,
        "1": -502
      },
      "size": {
        "0": 315,
        "1": 270
      },
      "flags": {},
      "order": 18,
      "mode": 0,
      "inputs": [
        {
          "name": "server_ip",
          "type": "STRING",
          "link": 234,
          "widget": {
            "name": "server_ip"
          }
        },
        {
          "name": "port",
          "type": "INT",
          "link": 245,
          "widget": {
            "name": "port"
          }
        }
      ],
      "outputs": [
        {
          "name": "VALUE",
          "type": "INT",
          "links": [
            108
          ],
          "shape": 3
        },
        {
          "name": "RAW_VALUE",
          "type": "FLOAT",
          "links": [
            109
          ],
          "shape": 3
        }
      ],
      "properties": {
        "Node name for S&R": "VrchIntOSCControlNode"
      },
      "widgets_values": [
        "192.168.123.104",
        8000,
        "/3/fader1",
        0,
        1,
        0,
        100,
        false,
        false
      ]
    },
    {
      "id": 120,
      "type": "easy showAnything",
      "pos": {
        "0": -1154,
        "1": -509
      },
      "size": {
        "0": 210,
        "1": 80
      },
      "flags": {},
      "order": 34,
      "mode": 0,
      "inputs": [
        {
          "name": "anything",
          "type": "*",
          "link": 108,
          "shape": 7
        }
      ],
      "outputs": [],
      "properties": {
        "Node name for S&R": "easy showAnything"
      },
      "widgets_values": [
        "0"
      ]
    },
    {
      "id": 123,
      "type": "easy showAnything",
      "pos": {
        "0": -1154,
        "1": -367
      },
      "size": {
        "0": 210,
        "1": 80
      },
      "flags": {},
      "order": 35,
      "mode": 0,
      "inputs": [
        {
          "name": "anything",
          "type": "*",
          "link": 109,
          "shape": 7
        }
      ],
      "outputs": [],
      "properties": {
        "Node name for S&R": "easy showAnything"
      },
      "widgets_values": [
        "0"
      ]
    },
    {
      "id": 121,
      "type": "VrchFloatOSCControlNode",
      "pos": {
        "0": -1548,
        "1": -119
      },
      "size": {
        "0": 315,
        "1": 270
      },
      "flags": {},
      "order": 19,
      "mode": 0,
      "inputs": [
        {
          "name": "server_ip",
          "type": "STRING",
          "link": 235,
          "widget": {
            "name": "server_ip"
          }
        },
        {
          "name": "port",
          "type": "INT",
          "link": 246,
          "widget": {
            "name": "port"
          }
        }
      ],
      "outputs": [
        {
          "name": "VALUE",
          "type": "FLOAT",
          "links": [
            94
          ],
          "slot_index": 0,
          "shape": 3
        },
        {
          "name": "RAW_VALUE",
          "type": "FLOAT",
          "links": [
            96
          ],
          "slot_index": 1,
          "shape": 3
        }
      ],
      "properties": {
        "Node name for S&R": "VrchFloatOSCControlNode"
      },
      "widgets_values": [
        "192.168.123.104",
        8000,
        "/3/fader2",
        0,
        1,
        false,
        100,
        false,
        false
      ]
    },
    {
      "id": 122,
      "type": "easy showAnything",
      "pos": {
        "0": -1142,
        "1": -123
      },
      "size": {
        "0": 210,
        "1": 80
      },
      "flags": {},
      "order": 36,
      "mode": 0,
      "inputs": [
        {
          "name": "anything",
          "type": "*",
          "link": 94,
          "shape": 7
        }
      ],
      "outputs": [],
      "properties": {
        "Node name for S&R": "easy showAnything"
      },
      "widgets_values": [
        "0.0"
      ]
    },
    {
      "id": 124,
      "type": "easy showAnything",
      "pos": {
        "0": -1135,
        "1": 14
      },
      "size": {
        "0": 210,
        "1": 80
      },
      "flags": {},
      "order": 37,
      "mode": 0,
      "inputs": [
        {
          "name": "anything",
          "type": "*",
          "link": 96,
          "shape": 7
        }
      ],
      "outputs": [],
      "properties": {
        "Node name for S&R": "easy showAnything"
      },
      "widgets_values": [
        "0.0"
      ]
    },
    {
      "id": 125,
      "type": "VrchSwitchOSCControlNode",
      "pos": {
        "0": -1540,
        "1": 242
      },
      "size": {
        "0": 315,
        "1": 438
      },
      "flags": {
        "collapsed": false
      },
      "order": 20,
      "mode": 0,
      "inputs": [
        {
          "name": "server_ip",
          "type": "STRING",
          "link": 236,
          "widget": {
            "name": "server_ip"
          }
        },
        {
          "name": "port",
          "type": "INT",
          "link": 247,
          "widget": {
            "name": "port"
          }
        }
      ],
      "outputs": [
        {
          "name": "SWITCH_1",
          "type": "BOOLEAN",
          "links": [
            97
          ],
          "slot_index": 0,
          "shape": 3
        },
        {
          "name": "SWITCH_2",
          "type": "BOOLEAN",
          "links": [
            98
          ],
          "slot_index": 1,
          "shape": 3
        },
        {
          "name": "SWITCH_3",
          "type": "BOOLEAN",
          "links": [
            99
          ],
          "slot_index": 2,
          "shape": 3
        },
        {
          "name": "SWITCH_4",
          "type": "BOOLEAN",
          "links": [
            100
          ],
          "slot_index": 3,
          "shape": 3
        },
        {
          "name": "SWITCH_5",
          "type": "BOOLEAN",
          "links": [
            101
          ],
          "slot_index": 4,
          "shape": 3
        },
        {
          "name": "SWITCH_6",
          "type": "BOOLEAN",
          "links": [
            102
          ],
          "slot_index": 5,
          "shape": 3
        },
        {
          "name": "SWITCH_7",
          "type": "BOOLEAN",
          "links": [
            103
          ],
          "slot_index": 6,
          "shape": 3
        },
        {
          "name": "SWITCH_8",
          "type": "BOOLEAN",
          "links": [
            104
          ],
          "slot_index": 7,
          "shape": 3
        }
      ],
      "properties": {
        "Node name for S&R": "VrchSwitchOSCControlNode"
      },
      "widgets_values": [
        "192.168.123.104",
        8000,
        "/3/push1",
        "/3/push2",
        "/3/push3",
        "/3/push4",
        "/3/toggle1",
        "/3/toggle2",
        "/3/toggle3",
        "/3/toggle4",
        false
      ]
    },
    {
      "id": 126,
      "type": "easy showAnything",
      "pos": {
        "0": -1117,
        "1": 243
      },
      "size": {
        "0": 210,
        "1": 80
      },
      "flags": {},
      "order": 38,
      "mode": 0,
      "inputs": [
        {
          "name": "anything",
          "type": "*",
          "link": 97,
          "shape": 7
        }
      ],
      "outputs": [],
      "properties": {
        "Node name for S&R": "easy showAnything"
      },
      "widgets_values": [
        "false"
      ]
    },
    {
      "id": 130,
      "type": "easy showAnything",
      "pos": {
        "0": -1111,
        "1": 385
      },
      "size": {
        "0": 210,
        "1": 80
      },
      "flags": {},
      "order": 39,
      "mode": 0,
      "inputs": [
        {
          "name": "anything",
          "type": "*",
          "link": 98,
          "shape": 7
        }
      ],
      "outputs": [],
      "properties": {
        "Node name for S&R": "easy showAnything"
      },
      "widgets_values": [
        "false"
      ]
    },
    {
      "id": 131,
      "type": "easy showAnything",
      "pos": {
        "0": -1111,
        "1": 519
      },
      "size": {
        "0": 210,
        "1": 80
      },
      "flags": {},
      "order": 40,
      "mode": 0,
      "inputs": [
        {
          "name": "anything",
          "type": "*",
          "link": 99,
          "shape": 7
        }
      ],
      "outputs": [],
      "properties": {
        "Node name for S&R": "easy showAnything"
      },
      "widgets_values": [
        "false"
      ]
    },
    {
      "id": 129,
      "type": "easy showAnything",
      "pos": {
        "0": -1108,
        "1": 654
      },
      "size": {
        "0": 210,
        "1": 80
      },
      "flags": {},
      "order": 41,
      "mode": 0,
      "inputs": [
        {
          "name": "anything",
          "type": "*",
          "link": 100,
          "shape": 7
        }
      ],
      "outputs": [],
      "properties": {
        "Node name for S&R": "easy showAnything"
      },
      "widgets_values": [
        "false"
      ]
    },
    {
      "id": 128,
      "type": "easy showAnything",
      "pos": {
        "0": -1100,
        "1": 790
      },
      "size": {
        "0": 210,
        "1": 80
      },
      "flags": {},
      "order": 42,
      "mode": 0,
      "inputs": [
        {
          "name": "anything",
          "type": "*",
          "link": 101,
          "shape": 7
        }
      ],
      "outputs": [],
      "properties": {
        "Node name for S&R": "easy showAnything"
      },
      "widgets_values": [
        "false"
      ]
    },
    {
      "id": 143,
      "type": "VrchTextConcatOSCControlNode",
      "pos": {
        "0": -2290,
        "1": 755
      },
      "size": {
        "0": 318.8970947265625,
        "1": 714
      },
      "flags": {},
      "order": 17,
      "mode": 0,
      "inputs": [
        {
          "name": "server_ip",
          "type": "STRING",
          "link": 233,
          "widget": {
            "name": "server_ip"
          }
        },
        {
          "name": "port",
          "type": "INT",
          "link": 244,
          "widget": {
            "name": "port"
          }
        }
      ],
      "outputs": [
        {
          "name": "TEXT_OUTPUT",
          "type": "STRING",
          "links": [
            107
          ],
          "slot_index": 0,
          "shape": 3
        }
      ],
      "properties": {
        "Node name for S&R": "VrchTextConcatOSCControlNode"
      },
      "widgets_values": [
        "red light",
        "blue light",
        "yellow light",
        "green light",
        "dog",
        "cat",
        "boy",
        "girl",
        "192.168.123.104",
        8000,
        "/3/toggle1",
        "/3/toggle2",
        "/3/toggle3",
        "/3/toggle4",
        "/3/toggle5",
        "/3/toggle6",
        "/3/toggle7",
        "/3/toggle8",
        ",",
        false
      ]
    },
    {
      "id": 138,
      "type": "ShowText|pysssss",
      "pos": {
        "0": -1912,
        "1": 760
      },
      "size": {
        "0": 210,
        "1": 85.58305358886719
      },
      "flags": {},
      "order": 33,
      "mode": 0,
      "inputs": [
        {
          "name": "text",
          "type": "STRING",
          "link": 107,
          "widget": {
            "name": "text"
          }
        }
      ],
      "outputs": [
        {
          "name": "STRING",
          "type": "STRING",
          "links": null,
          "shape": 6
        }
      ],
      "properties": {
        "Node name for S&R": "ShowText|pysssss"
      },
      "widgets_values": [
        ""
      ]
    },
    {
      "id": 142,
      "type": "ShowText|pysssss",
      "pos": {
        "0": -1539,
        "1": 941
      },
      "size": {
        "0": 315,
        "1": 76
      },
      "flags": {},
      "order": 46,
      "mode": 0,
      "inputs": [
        {
          "name": "text",
          "type": "STRING",
          "link": 106,
          "widget": {
            "name": "text"
          }
        }
      ],
      "outputs": [
        {
          "name": "STRING",
          "type": "STRING",
          "links": null,
          "shape": 6
        }
      ],
      "properties": {
        "Node name for S&R": "ShowText|pysssss"
      },
      "widgets_values": [
        ""
      ]
    },
    {
      "id": 204,
      "type": "PreviewImage",
      "pos": {
        "0": -1886,
        "1": 2180
      },
      "size": {
        "0": 210,
        "1": 246
      },
      "flags": {},
      "order": 56,
      "mode": 0,
      "inputs": [
        {
          "name": "images",
          "type": "IMAGE",
          "link": 208
        }
      ],
      "outputs": [],
      "properties": {
        "Node name for S&R": "PreviewImage"
      },
      "widgets_values": []
    },
    {
      "id": 207,
      "type": "VrchImageSwitchOSCControlNode",
      "pos": {
        "0": -2265,
        "1": 2171
      },
      "size": {
        "0": 315,
        "1": 270
      },
      "flags": {},
      "order": 25,
      "mode": 0,
      "inputs": [
        {
          "name": "image0",
          "type": "IMAGE",
          "link": 205,
          "shape": 7
        },
        {
          "name": "image1",
          "type": "IMAGE",
          "link": 206,
          "shape": 7
        },
        {
          "name": "image2",
          "type": "IMAGE",
          "link": 207,
          "shape": 7
        },
        {
          "name": "image3",
          "type": "IMAGE",
          "link": null,
          "shape": 7
        },
        {
          "name": "server_ip",
          "type": "STRING",
          "link": 241,
          "widget": {
            "name": "server_ip"
          }
        },
        {
          "name": "port",
          "type": "INT",
          "link": 252,
          "widget": {
            "name": "port"
          }
        }
      ],
      "outputs": [
        {
          "name": "IMAGE",
          "type": "IMAGE",
          "links": [
            208
          ],
          "shape": 3
        }
      ],
      "properties": {
        "Node name for S&R": "VrchImageSwitchOSCControlNode"
      },
      "widgets_values": [
        "192.168.123.104",
        8000,
        "/3/radio1",
        true
      ]
    },
    {
      "id": 211,
      "type": "Note",
      "pos": {
        "0": -3476,
        "1": 765
      },
      "size": {
        "0": 535.8948364257812,
        "1": 163.19281005859375
      },
      "flags": {},
      "order": 10,
      "mode": 0,
      "inputs": [],
      "outputs": [],
      "title": "Instructions",
      "properties": {
        "text": ""
      },
      "widgets_values": [
        "1. Change Server IP Address to your ComfyUI server IP address.\n2. Search and install app \"TouchOSC\".\n3. Import and open \"comfyui_osc_control.tosc\" control panel.\n4. Test OSC Control nodes by using the actions in \"Test\" tab.\n5. Please check \"ComfyUI Web Viewer\" repo for more details:\n   - https://github.com/VrchStudio/comfyui-web-viewer\n\nby Tianzi@vrch.io"
      ],
      "color": "#432",
      "bgcolor": "#653"
    },
    {
      "id": 186,
      "type": "LoadImage",
      "pos": {
        "0": -2670,
        "1": 2120
      },
      "size": {
        "0": 315,
        "1": 314.00006103515625
      },
      "flags": {},
      "order": 11,
      "mode": 0,
      "inputs": [],
      "outputs": [
        {
          "name": "IMAGE",
          "type": "IMAGE",
          "links": [
            205
          ],
          "slot_index": 0,
          "shape": 3
        },
        {
          "name": "MASK",
          "type": "MASK",
          "links": null,
          "shape": 3
        }
      ],
      "properties": {
        "Node name for S&R": "LoadImage"
      },
      "widgets_values": [
        "11.jpg",
        "image"
      ]
    },
    {
      "id": 187,
      "type": "LoadImage",
      "pos": {
        "0": -2666,
        "1": 2473
      },
      "size": {
        "0": 303.4268798828125,
        "1": 314
      },
      "flags": {},
      "order": 12,
      "mode": 0,
      "inputs": [],
      "outputs": [
        {
          "name": "IMAGE",
          "type": "IMAGE",
          "links": [
            206
          ],
          "slot_index": 0,
          "shape": 3
        },
        {
          "name": "MASK",
          "type": "MASK",
          "links": null,
          "shape": 3
        }
      ],
      "properties": {
        "Node name for S&R": "LoadImage"
      },
      "widgets_values": [
        "12.jpg",
        "image"
      ]
    },
    {
      "id": 202,
      "type": "LoadImage",
      "pos": {
        "0": -2664,
        "1": 2839
      },
      "size": {
        "0": 296.40509033203125,
        "1": 314
      },
      "flags": {},
      "order": 13,
      "mode": 0,
      "inputs": [],
      "outputs": [
        {
          "name": "IMAGE",
          "type": "IMAGE",
          "links": [
            207
          ],
          "slot_index": 0,
          "shape": 3
        },
        {
          "name": "MASK",
          "type": "MASK",
          "links": null,
          "shape": 3
        }
      ],
      "properties": {
        "Node name for S&R": "LoadImage"
      },
      "widgets_values": [
        "9.jpg",
        "image"
      ]
    },
    {
      "id": 212,
      "type": "VrchOSCControlSettingsNode",
      "pos": {
        "0": -3378,
        "1": 1100
      },
      "size": {
        "0": 378,
        "1": 126
      },
      "flags": {},
      "order": 14,
      "mode": 0,
      "inputs": [],
      "outputs": [
        {
          "name": "SERVER_IP",
          "type": "STRING",
          "links": [
            231,
            232,
            233,
            234,
            235,
            236,
            237,
            238,
            239,
            240,
            241
          ]
        },
        {
          "name": "PORT",
          "type": "INT",
          "links": [
            242,
            243,
            244,
            245,
            246,
            247,
            248,
            249,
            250,
            251,
            252
          ]
        }
      ],
      "properties": {
        "Node name for S&R": "VrchOSCControlSettingsNode"
      },
      "widgets_values": [
        "192.168.123.104",
        8000,
        false
      ]
    }
  ],
  "links": [
    [
      94,
      121,
      0,
      122,
      0,
      "*"
    ],
    [
      96,
      121,
      1,
      124,
      0,
      "*"
    ],
    [
      97,
      125,
      0,
      126,
      0,
      "*"
    ],
    [
      98,
      125,
      1,
      130,
      0,
      "*"
    ],
    [
      99,
      125,
      2,
      131,
      0,
      "*"
    ],
    [
      100,
      125,
      3,
      129,
      0,
      "*"
    ],
    [
      101,
      125,
      4,
      128,
      0,
      "*"
    ],
    [
      102,
      125,
      5,
      134,
      0,
      "*"
    ],
    [
      103,
      125,
      6,
      133,
      0,
      "*"
    ],
    [
      104,
      125,
      7,
      132,
      0,
      "*"
    ],
    [
      106,
      141,
      0,
      142,
      0,
      "STRING"
    ],
    [
      107,
      143,
      0,
      138,
      0,
      "STRING"
    ],
    [
      108,
      144,
      0,
      120,
      0,
      "*"
    ],
    [
      109,
      144,
      1,
      123,
      0,
      "*"
    ],
    [
      110,
      145,
      0,
      99,
      0,
      "*"
    ],
    [
      111,
      145,
      1,
      100,
      0,
      "*"
    ],
    [
      112,
      146,
      0,
      116,
      0,
      "*"
    ],
    [
      113,
      146,
      1,
      118,
      0,
      "*"
    ],
    [
      114,
      146,
      2,
      117,
      0,
      "*"
    ],
    [
      119,
      152,
      0,
      149,
      0,
      "*"
    ],
    [
      120,
      152,
      1,
      151,
      0,
      "*"
    ],
    [
      121,
      152,
      2,
      150,
      0,
      "*"
    ],
    [
      122,
      152,
      3,
      148,
      0,
      "*"
    ],
    [
      123,
      145,
      2,
      153,
      0,
      "*"
    ],
    [
      124,
      145,
      3,
      154,
      0,
      "*"
    ],
    [
      133,
      166,
      0,
      168,
      0,
      "*"
    ],
    [
      134,
      167,
      0,
      168,
      1,
      "*"
    ],
    [
      135,
      168,
      0,
      163,
      0,
      "*"
    ],
    [
      136,
      171,
      0,
      172,
      0,
      "*"
    ],
    [
      137,
      171,
      1,
      173,
      0,
      "*"
    ],
    [
      138,
      171,
      2,
      174,
      0,
      "*"
    ],
    [
      139,
      171,
      3,
      175,
      0,
      "*"
    ],
    [
      140,
      176,
      0,
      171,
      0,
      "*"
    ],
    [
      141,
      177,
      0,
      171,
      1,
      "*"
    ],
    [
      142,
      178,
      0,
      171,
      2,
      "*"
    ],
    [
      143,
      179,
      0,
      171,
      3,
      "*"
    ],
    [
      144,
      180,
      0,
      171,
      4,
      "*"
    ],
    [
      145,
      181,
      0,
      171,
      5,
      "*"
    ],
    [
      146,
      182,
      0,
      171,
      6,
      "*"
    ],
    [
      147,
      183,
      0,
      171,
      7,
      "*"
    ],
    [
      205,
      186,
      0,
      207,
      0,
      "IMAGE"
    ],
    [
      206,
      187,
      0,
      207,
      1,
      "IMAGE"
    ],
    [
      207,
      202,
      0,
      207,
      2,
      "IMAGE"
    ],
    [
      208,
      207,
      0,
      204,
      0,
      "IMAGE"
    ],
    [
      231,
      212,
      0,
      145,
      0,
      "STRING"
    ],
    [
      232,
      212,
      0,
      146,
      0,
      "STRING"
    ],
    [
      233,
      212,
      0,
      143,
      0,
      "STRING"
    ],
    [
      234,
      212,
      0,
      144,
      0,
      "STRING"
    ],
    [
      235,
      212,
      0,
      121,
      0,
      "STRING"
    ],
    [
      236,
      212,
      0,
      125,
      0,
      "STRING"
    ],
    [
      237,
      212,
      0,
      141,
      0,
      "STRING"
    ],
    [
      238,
      212,
      0,
      152,
      0,
      "STRING"
    ],
    [
      239,
      212,
      0,
      168,
      2,
      "STRING"
    ],
    [
      240,
      212,
      0,
      171,
      8,
      "STRING"
    ],
    [
      241,
      212,
      0,
      207,
      4,
      "STRING"
    ],
    [
      242,
      212,
      1,
      145,
      1,
      "INT"
    ],
    [
      243,
      212,
      1,
      146,
      1,
      "INT"
    ],
    [
      244,
      212,
      1,
      143,
      1,
      "INT"
    ],
    [
      245,
      212,
      1,
      144,
      1,
      "INT"
    ],
    [
      246,
      212,
      1,
      121,
      1,
      "INT"
    ],
    [
      247,
      212,
      1,
      125,
      1,
      "INT"
    ],
    [
      248,
      212,
      1,
      141,
      1,
      "INT"
    ],
    [
      249,
      212,
      1,
      152,
      1,
      "INT"
    ],
    [
      250,
      212,
      1,
      168,
      3,
      "INT"
    ],
    [
      251,
      212,
      1,
      171,
      9,
      "INT"
    ],
    [
      252,
      212,
      1,
      207,
      5,
      "INT"
    ]
  ],
  "groups": [
    {
      "title": "OSC Server Settings",
      "bounding": [
        -3466,
        965,
        567,
        398
      ],
      "color": "#3f789e",
      "font_size": 24,
      "flags": {}
    }
  ],
  "config": {},
  "extra": {
    "ds": {
      "scale": 0.25401326852419986,
      "offset": [
        5232.713703038195,
        208.52509373263888
      ]
    }
  },
  "version": 0.4
}